[
null,
{"id":1,"autoRemovalTiming":0,"chanceByDamage":100,"iconIndex":1,"maxTurns":1,"message1":" has fallen!","message2":" is slain!","message3":"","message4":" has risen.","minTurns":1,"motion":3,"name":"Knockout","note":"State #1 will be automatically added when\r\nHP reaches 0.","overlay":0,"priority":100,"releaseByDamage":false,"removeAtBattleEnd":false,"removeByDamage":false,"removeByRestriction":false,"removeByWalking":false,"restriction":4,"stepsToRemove":100,"traits":[{"code":23,"dataId":9,"value":0}],"params":[],"damage":{"critical":"","elementId":"","formula":"","type":"","variance":""}},
{"id":2,"autoRemovalTiming":2,"chanceByDamage":100,"iconIndex":0,"maxTurns":1,"message1":" is guarding!","message2":" has guarded!","message3":"","message4":"","minTurns":1,"motion":0,"name":"Guard","note":"","overlay":0,"priority":0,"removeAtBattleEnd":true,"removeByDamage":false,"removeByRestriction":true,"removeByWalking":false,"restriction":0,"stepsToRemove":100,"traits":[{"code":62,"dataId":1,"value":0}],"description":"","params":[],"damage":{"critical":"","elementId":"","formula":"","type":"","variance":""}},
{"id":3,"autoRemovalTiming":2,"chanceByDamage":100,"iconIndex":2,"maxTurns":6,"message1":" has been poisoned!","message2":" is poisoned!","message3":" takes poison damage!","message4":" is no longer poisoned.","minTurns":3,"motion":1,"name":"Poison","note":"","overlay":1,"priority":5,"removeAtBattleEnd":false,"removeByDamage":false,"removeByRestriction":false,"removeByWalking":true,"restriction":0,"stepsToRemove":20,"traits":[{"code":22,"dataId":7,"value":-0.05}],"params":[],"damage":{"critical":"","elementId":"","formula":"","type":"","variance":""}},
{"id":4,"autoRemovalTiming":1,"chanceByDamage":100,"iconIndex":3,"maxTurns":6,"message1":" has been blinded!","message2":" is now blind!","message3":" is still blind!","message4":" is no longer blind.","minTurns":3,"motion":1,"name":"Blind","note":"","overlay":2,"priority":10,"removeAtBattleEnd":true,"removeByDamage":false,"removeByRestriction":false,"removeByWalking":false,"restriction":0,"stepsToRemove":100,"traits":[{"code":22,"dataId":0,"value":-0.75}],"params":[],"damage":{"critical":"","elementId":"","formula":"","type":"","variance":""}},
{"id":5,"autoRemovalTiming":1,"chanceByDamage":100,"iconIndex":4,"maxTurns":6,"message1":" has been silenced!","message2":" is now silent!","message3":" is still silent!","message4":" is no longer silent.","minTurns":3,"motion":1,"name":"Silence","note":"","overlay":3,"priority":15,"removeAtBattleEnd":true,"removeByDamage":false,"removeByRestriction":false,"removeByWalking":false,"restriction":0,"stepsToRemove":100,"traits":[{"code":42,"dataId":3,"value":1},{"code":42,"dataId":4,"value":1},{"code":42,"dataId":6,"value":1}],"params":[],"damage":{"critical":"","elementId":"","formula":"","type":"","variance":""}},
{"id":6,"autoRemovalTiming":2,"chanceByDamage":100,"iconIndex":12,"maxTurns":6,"message1":" has been set on fire!","message2":" is now burning!","message3":" takes burning damge!","message4":" is no longer on fire.","minTurns":3,"motion":1,"name":"Burn","note":"","overlay":9,"priority":20,"removeAtBattleEnd":false,"removeByDamage":false,"removeByRestriction":false,"removeByWalking":true,"restriction":0,"stepsToRemove":35,"traits":[{"code":22,"dataId":7,"value":-0.05},{"code":21,"dataId":3,"value":0.25}],"params":[],"damage":{"critical":"","elementId":"","formula":"","type":"","variance":""}},
{"id":7,"autoRemovalTiming":2,"chanceByDamage":60,"iconIndex":11,"maxTurns":6,"message1":" has been frozen!","message2":" is now frozen!","message3":" is still frozen!","message4":" is no longer frozen.","minTurns":3,"motion":2,"name":"Frozen","note":"","overlay":10,"priority":60,"removeAtBattleEnd":false,"removeByDamage":true,"removeByRestriction":false,"removeByWalking":true,"restriction":4,"stepsToRemove":5,"traits":[{"code":22,"dataId":8,"value":-0.1},{"code":22,"dataId":9,"value":-0.1}],"params":[],"damage":{"critical":"","elementId":"","formula":"","type":"","variance":""}},
{"id":8,"autoRemovalTiming":1,"chanceByDamage":20,"iconIndex":5,"maxTurns":6,"message1":" has been enraged!","message2":" is now enraged!","message3":" is still enraged!","message4":" is no longer angry.","minTurns":3,"motion":0,"name":"Fury","note":"","overlay":4,"priority":50,"removeAtBattleEnd":true,"removeByDamage":true,"removeByRestriction":false,"removeByWalking":false,"restriction":1,"stepsToRemove":100,"traits":[],"params":[],"damage":{"critical":"","elementId":"","formula":"","type":"","variance":""}},
{"id":9,"autoRemovalTiming":2,"chanceByDamage":10,"iconIndex":6,"maxTurns":6,"message1":" has become confused!","message2":" is now confused!","message3":" is still confused!","message4":" is no longer confused.","minTurns":3,"motion":0,"name":"Confusion","note":"","overlay":5,"priority":55,"removeAtBattleEnd":true,"removeByDamage":true,"removeByRestriction":false,"removeByWalking":false,"restriction":2,"stepsToRemove":100,"traits":[],"params":[],"damage":{"critical":"","elementId":"","formula":"","type":"","variance":""}},
{"id":10,"autoRemovalTiming":2,"chanceByDamage":10,"iconIndex":8,"maxTurns":6,"message1":" has become sleepy!","message2":" is now asleep!","message3":" is still sleeping.","message4":" is no longer sleeping.","minTurns":3,"motion":2,"name":"Sleep","note":"","overlay":7,"priority":57,"removeAtBattleEnd":true,"removeByDamage":true,"removeByRestriction":false,"removeByWalking":false,"restriction":4,"stepsToRemove":100,"traits":[],"params":[],"damage":{"critical":"","elementId":"","formula":"","type":"","variance":""}},
{"id":11,"autoRemovalTiming":2,"chanceByDamage":100,"iconIndex":81,"maxTurns":6,"message1":" is on guard to protect their allies.","message2":"","message3":"","message4":" is no longer protecting their allies.","minTurns":5,"motion":0,"name":"Protection","note":"","overlay":0,"priority":0,"removeAtBattleEnd":true,"removeByDamage":false,"removeByRestriction":false,"removeByWalking":false,"restriction":0,"stepsToRemove":100,"traits":[{"code":62,"dataId":2,"value":1}],"params":[],"damage":{"critical":"","elementId":"","formula":"","type":"","variance":""}},
{"id":12,"autoRemovalTiming":0,"chanceByDamage":100,"iconIndex":70,"maxTurns":1,"message1":" is now blessed!","message2":"","message3":"","message4":" is no longer blessed.","minTurns":1,"motion":0,"name":"Blessed","note":"The auto-life one.","overlay":6,"priority":100,"removeAtBattleEnd":true,"removeByDamage":false,"removeByRestriction":false,"removeByWalking":false,"restriction":0,"stepsToRemove":100,"traits":[],"params":[],"damage":{"critical":"","elementId":"","formula":"","type":"","variance":""}},
{"id":13,"autoRemovalTiming":2,"chanceByDamage":100,"iconIndex":162,"maxTurns":6,"message1":" has protection against ice.","message2":" has protection against ice.","message3":"","message4":" no longer has protection against ice.","minTurns":3,"motion":0,"name":"Fire Barrier","note":"","overlay":0,"priority":100,"removeAtBattleEnd":true,"removeByDamage":false,"removeByRestriction":false,"removeByWalking":false,"restriction":0,"stepsToRemove":100,"traits":[{"code":11,"dataId":5,"value":0},{"code":14,"dataId":7,"value":1}],"params":[],"damage":{"critical":"","elementId":"","formula":"","type":"","variance":""}},
{"id":14,"autoRemovalTiming":2,"chanceByDamage":100,"iconIndex":165,"maxTurns":6,"message1":" has protection against fire.","message2":" has protection against fire.","message3":"","message4":" no longer has protection against fire.","minTurns":3,"motion":0,"name":"Ice Barrier","note":"","overlay":0,"priority":100,"removeAtBattleEnd":true,"removeByDamage":false,"removeByRestriction":false,"removeByWalking":false,"restriction":0,"stepsToRemove":100,"traits":[{"code":11,"dataId":4,"value":0},{"code":14,"dataId":6,"value":1}],"params":[],"damage":{"critical":"","elementId":"","formula":"","type":"","variance":""}},
{"id":15,"autoRemovalTiming":2,"chanceByDamage":100,"iconIndex":160,"maxTurns":6,"message1":" has protection against fire & ice.","message2":" has protection against fire & ice.","message3":"","message4":" no longer has protection against fire & ice.","minTurns":3,"motion":0,"name":"Barrier","note":"","overlay":0,"priority":0,"removeAtBattleEnd":true,"removeByDamage":false,"removeByRestriction":false,"removeByWalking":false,"restriction":0,"stepsToRemove":100,"traits":[{"code":11,"dataId":4,"value":0},{"code":11,"dataId":5,"value":0},{"code":14,"dataId":6,"value":1},{"code":14,"dataId":7,"value":1}],"params":[],"damage":{"critical":"","elementId":"","formula":"","type":"","variance":""}},
{"id":16,"autoRemovalTiming":2,"chanceByDamage":100,"iconIndex":161,"maxTurns":6,"message1":" has protection against all elements.","message2":" has protection against all elements.","message3":"","message4":" no longer  has protection against all elements.","minTurns":3,"motion":0,"name":"Ultimate Barrier","note":"","overlay":0,"priority":0,"removeAtBattleEnd":true,"removeByDamage":false,"removeByRestriction":false,"removeByWalking":false,"restriction":0,"stepsToRemove":100,"traits":[{"code":11,"dataId":3,"value":0},{"code":11,"dataId":4,"value":0},{"code":11,"dataId":5,"value":0},{"code":11,"dataId":6,"value":0},{"code":11,"dataId":7,"value":0},{"code":11,"dataId":8,"value":0},{"code":14,"dataId":3,"value":1},{"code":14,"dataId":4,"value":1},{"code":14,"dataId":6,"value":1},{"code":14,"dataId":5,"value":1},{"code":14,"dataId":7,"value":1},{"code":14,"dataId":8,"value":1},{"code":14,"dataId":9,"value":1},{"code":14,"dataId":10,"value":1}],"params":[],"damage":{"critical":"","elementId":"","formula":"","type":"","variance":""}},
{"id":17,"autoRemovalTiming":2,"chanceByDamage":100,"iconIndex":89,"maxTurns":4,"message1":" is stuck in time for four turns.","message2":" is stuck in time for four turns.","message3":"","message4":" is no longer stuck in time.","minTurns":4,"motion":2,"name":"Suspend","note":"","overlay":0,"priority":0,"removeAtBattleEnd":true,"removeByDamage":false,"removeByRestriction":false,"removeByWalking":false,"restriction":4,"stepsToRemove":100,"traits":[],"params":[],"damage":{"critical":"","elementId":"","formula":"","type":"","variance":""}},
{"id":18,"autoRemovalTiming":2,"chanceByDamage":100,"iconIndex":89,"maxTurns":1,"message1":" is stuck in time for one turn.","message2":" is stuck in time for one turn.","message3":"","message4":" is no longer stuck in time.","minTurns":1,"motion":2,"name":"Pause","note":"","overlay":0,"priority":0,"removeAtBattleEnd":true,"removeByDamage":false,"removeByRestriction":false,"removeByWalking":false,"restriction":4,"stepsToRemove":100,"traits":[],"params":[],"damage":{"critical":"","elementId":"","formula":"","type":"","variance":""}},
{"id":19,"autoRemovalTiming":2,"chanceByDamage":100,"iconIndex":87,"maxTurns":4,"message1":"","message2":"","message3":"","message4":"","minTurns":4,"motion":0,"name":"Rise Critcal","note":"","overlay":0,"priority":0,"removeAtBattleEnd":true,"removeByDamage":false,"removeByRestriction":false,"removeByWalking":false,"restriction":0,"stepsToRemove":100,"traits":[{"code":22,"dataId":2,"value":0.5}],"params":[],"damage":{"critical":"","elementId":"","formula":"","type":"","variance":""}},
{"id":20,"autoRemovalTiming":0,"chanceByDamage":100,"iconIndex":0,"maxTurns":1,"message1":"","message2":"","message3":"","message4":"","minTurns":1,"motion":0,"name":"STOLEN","note":"","overlay":0,"priority":0,"removeAtBattleEnd":true,"removeByDamage":false,"removeByRestriction":false,"removeByWalking":false,"restriction":0,"stepsToRemove":100,"traits":[],"params":[],"damage":{"critical":"","elementId":"","formula":"","type":"","variance":""}},
{"id":21,"autoRemovalTiming":2,"chanceByDamage":100,"iconIndex":0,"maxTurns":1,"message1":"","message2":"","message3":"","message4":"","minTurns":1,"motion":0,"name":"CutMagic","note":"","overlay":0,"priority":50,"removeAtBattleEnd":false,"removeByDamage":false,"removeByRestriction":false,"removeByWalking":false,"restriction":0,"stepsToRemove":100,"traits":[{"code":22,"dataId":8,"value":-0.1}],"params":[],"damage":{"critical":"","elementId":"","formula":"","type":"","variance":""}},
{"id":22,"autoRemovalTiming":2,"chanceByDamage":100,"iconIndex":0,"maxTurns":1,"message1":"","message2":"","message3":"","message4":"","minTurns":1,"motion":0,"name":"CutTech","note":"","overlay":0,"priority":50,"removeAtBattleEnd":false,"removeByDamage":false,"removeByRestriction":false,"removeByWalking":false,"restriction":0,"stepsToRemove":100,"traits":[{"code":22,"dataId":9,"value":-0.1}],"params":[],"damage":{"critical":"","elementId":"","formula":"","type":"","variance":""}}
]